{
  "fecha_str": "7 de mayo de 2026",
  "fecha_iso": "2026-05-07",
  "dias_atraso": 0,
  "n_cotizaciones": 19,
  "texto_resumen": "Hoy se relevaron <b>19 cotizaciones</b> en el MCBA para tus productos. 7 cotizaciones bajaron, 0 subieron y 6 se mantuvieron estables respecto al día hábil anterior.",
  "productos_top": [
    {
      "especie": "TOMATE",
      "variedad": "CHERRY",
      "procedencia": "BS. AS. *",
      "envase": "cajón",
      "kg_bulto": 5.0,
      "precio": 5750.0,
      "variacion": -23.076923076923077
    },
    {
      "especie": "TOMATE",
      "variedad": "PERITA",
      "procedencia": "JUJUY",
      "envase": "cajón tomate",
      "kg_bulto": 18.0,
      "precio": 20000.0,
      "variacion": -21.73913043478261
    },
    {
      "especie": "TOMATE",
      "variedad": "REDONDO",
      "procedencia": "BS. AS. *",
      "envase": "cajón tomate",
      "kg_bulto": 18.0,
      "precio": 17333.333333333332,
      "variacion": -40.909090909090914
    },
    {
      "especie": "PIMIENTO",
      "variedad": "MORRON",
      "procedencia": "SALTA",
      "envase": "pelado",
      "kg_bulto": 10.0,
      "precio": 18000.0,
      "variacion": -39.130434782608695
    },
    {
      "especie": "PEPINO",
      "variedad": "",
      "procedencia": "SALTA",
      "envase": "cajón tomate",
      "kg_bulto": 18.0,
      "precio": 26000.0,
      "variacion": 0.0
    },
    {
      "especie": "BERENJENA",
      "variedad": "VTA.MED.LA",
      "procedencia": "SALTA",
      "envase": "pelado",
      "kg_bulto": 10.0,
      "precio": 15000.0,
      "variacion": -6.25
    },
    {
      "especie": "ZAPALLITO",
      "variedad": "LARGO",
      "procedencia": "JUJUY",
      "envase": "pelado",
      "kg_bulto": 15.0,
      "precio": 18000.0,
      "variacion": 0.0
    },
    {
      "especie": "ZAPALLITO",
      "variedad": "REDONDO",
      "procedencia": "JUJUY",
      "envase": "pelado",
      "kg_bulto": 15.0,
      "precio": 24000.0,
      "variacion": -4.166666666666666
    },
    {
      "especie": "ZAPALLO",
      "variedad": "ANQUITO",
      "procedencia": "BS. AS. *",
      "envase": "jaula",
      "kg_bulto": 20.0,
      "precio": 5300.0,
      "variacion": -3.6363636363636362
    },
    {
      "especie": "CHOCLO",
      "variedad": "AMARILLO",
      "procedencia": "JUJUY",
      "envase": "pelado",
      "kg_bulto": 15.0,
      "precio": 20000.0,
      "variacion": -13.043478260869565
    },
    {
      "especie": "CHAUCHA",
      "variedad": "ESPA¥OLA",
      "procedencia": "BS. AS. *",
      "envase": "cajón tomate",
      "kg_bulto": 10.0,
      "precio": 11000.0,
      "variacion": 0.0
    },
    {
      "especie": "CHAUCHA",
      "variedad": "ROLLIZA",
      "procedencia": "SALTA",
      "envase": "cajón tomate",
      "kg_bulto": 12.0,
      "precio": 23000.0,
      "variacion": 4.545454545454546
    }
  ],
  "clima_48h": [
    {
      "zona": "Orán",
      "provincia": "Salta",
      "tmax": 22.3,
      "tmin": 12.2,
      "lluvia_mm": 0,
      "prob_lluvia": 0,
      "tmax_pasado": 19.0,
      "tmin_pasado": 9.9,
      "lluvia_pasado": 0,
      "prob_lluvia_pasado": 0,
      "alerta": null
    },
    {
      "zona": "Pichanal",
      "provincia": "Salta",
      "tmax": 21.9,
      "tmin": 13.2,
      "lluvia_mm": 0,
      "prob_lluvia": 0,
      "tmax_pasado": 19.9,
      "tmin_pasado": 9.4,
      "lluvia_pasado": 0,
      "prob_lluvia_pasado": 0,
      "alerta": null
    },
    {
      "zona": "Colonia Santa Rosa",
      "provincia": "Salta",
      "tmax": 19.8,
      "tmin": 12.6,
      "lluvia_mm": 0.3,
      "prob_lluvia": 33,
      "tmax_pasado": 15.9,
      "tmin_pasado": 9.0,
      "lluvia_pasado": 0,
      "prob_lluvia_pasado": 4,
      "alerta": null
    },
    {
      "zona": "General Pizarro",
      "provincia": "Salta",
      "tmax": 17.2,
      "tmin": 8.6,
      "lluvia_mm": 0,
      "prob_lluvia": 0,
      "tmax_pasado": 13.1,
      "tmin_pasado": 6.7,
      "lluvia_pasado": 0,
      "prob_lluvia_pasado": 8,
      "alerta": null
    },
    {
      "zona": "Apolinario Saravia",
      "provincia": "Salta",
      "tmax": 22.1,
      "tmin": 10.4,
      "lluvia_mm": 0,
      "prob_lluvia": 0,
      "tmax_pasado": 17.6,
      "tmin_pasado": 9.2,
      "lluvia_pasado": 0.3,
      "prob_lluvia_pasado": 0,
      "alerta": null
    },
    {
      "zona": "Yuto",
      "provincia": "Jujuy",
      "tmax": 21.5,
      "tmin": 11.8,
      "lluvia_mm": 0,
      "prob_lluvia": 8,
      "tmax_pasado": 18.2,
      "tmin_pasado": 9.2,
      "lluvia_pasado": 0,
      "prob_lluvia_pasado": 6,
      "alerta": null
    },
    {
      "zona": "Fraile Pintado",
      "provincia": "Jujuy",
      "tmax": 19.5,
      "tmin": 10.6,
      "lluvia_mm": 0,
      "prob_lluvia": 2,
      "tmax_pasado": 15.9,
      "tmin_pasado": 8.2,
      "lluvia_pasado": 0,
      "prob_lluvia_pasado": 4,
      "alerta": null
    },
    {
      "zona": "Chalicán",
      "provincia": "Jujuy",
      "tmax": 20.5,
      "tmin": 11.4,
      "lluvia_mm": 0,
      "prob_lluvia": 2,
      "tmax_pasado": 15.6,
      "tmin_pasado": 8.9,
      "lluvia_pasado": 0,
      "prob_lluvia_pasado": 4,
      "alerta": null
    },
    {
      "zona": "Aguas Calientes",
      "provincia": "Jujuy",
      "tmax": 12.8,
      "tmin": 6.0,
      "lluvia_mm": 0,
      "prob_lluvia": 0,
      "tmax_pasado": 9.2,
      "tmin_pasado": 2.9,
      "lluvia_pasado": 0,
      "prob_lluvia_pasado": 57,
      "alerta": "💨 Viento fuerte (53 km/h) · ❄️ Riesgo de helada (3°C)"
    },
    {
      "zona": "Santa Clara",
      "provincia": "Jujuy",
      "tmax": 16.3,
      "tmin": 8.8,
      "lluvia_mm": 0,
      "prob_lluvia": 0,
      "tmax_pasado": 12.9,
      "tmin_pasado": 6.8,
      "lluvia_pasado": 0,
      "prob_lluvia_pasado": 33,
      "alerta": null
    }
  ],
  "alertas_7d": [
    {
      "zona": "Aguas Calientes",
      "provincia": "Jujuy",
      "alertas": [
        {
          "tipo": "Viento fuerte",
          "icono": "💨",
          "severidad": "MEDIA",
          "valor": "53 km/h",
          "detalle": "Ráfagas hasta 53 km/h",
          "fecha": "2026-05-08"
        },
        {
          "tipo": "Riesgo de helada",
          "icono": "❄️",
          "severidad": "MEDIA",
          "valor": "3°C",
          "detalle": "Mínima 3°C",
          "fecha": "2026-05-09"
        },
        {
          "tipo": "Riesgo de helada",
          "icono": "❄️",
          "severidad": "MEDIA",
          "valor": "2°C",
          "detalle": "Mínima 2°C",
          "fecha": "2026-05-10"
        },
        {
          "tipo": "Riesgo de helada",
          "icono": "❄️",
          "severidad": "MEDIA",
          "valor": "3°C",
          "detalle": "Mínima 3°C",
          "fecha": "2026-05-11"
        }
      ]
    }
  ]
}